docker_lens/__init__.py
docker_lens/cli.py
docker_lens/commands/__init__.py
docker_lens/commands/debug.py
docker_lens/commands/exists.py
docker_lens/commands/ps.py
docker_lens/core/__init__.py
docker_lens/core/config.py
docker_lens/core/constants.py
docker_lens/core/docker.py
docker_lens/utils/__init__.py
docker_lens/utils/name.py
docker_lens/utils/pull.py
docker_lens-0.1.1.dist-info/licenses/LICENSE
docker_lens-0.1.1.dist-info/METADATA
docker_lens-0.1.1.dist-info/WHEEL
docker_lens-0.1.1.dist-info/entry_points.txt
docker_lens-0.1.1.dist-info/top_level.txt
docker_lens-0.1.1.dist-info/RECORD
