Metadata-Version: 2.4
Name: docker-lens
Version: 0.1.1
Summary: A Docker debugging CLI tool
Author-email: Kaveh Moradian <kave.moradian@gmail.com>
License-Expression: GPL-3.0-or-later
Requires-Python: >=3.9
License-File: LICENSE
Requires-Dist: docker>=7.1.0
Requires-Dist: click>=8.3.1
Requires-Dist: rich>=14.2.0
Requires-Dist: PyYAML>=6.0.3
Requires-Dist: dockerpty>=0.4.1
Dynamic: license-file
